{
  "Actor": {
    "types": [
      "acolyte",
      "npc"
    ],
    "templates": {
      "characteristics": {
        "characteristics": {
          "weaponSkill": {
            "label": "CHARACTERISTIC.WEAPON_SKILL",
            "short": "WS",
            "base": 0,
            "advance": 0,
            "unnatural": 0,
            "cost": 0
          },
          "ballisticSkill": {
            "label": "CHARACTERISTIC.BALLISTIC_SKILL",
            "short": "BS",
            "base": 0,
            "advance": 0,
            "unnatural": 0,
            "cost": 0
          },
          "strength": {
            "label": "CHARACTERISTIC.STRENGTH",
            "short": "S",
            "base": 0,
            "advance": 0,
            "unnatural": 0,
            "cost": 0
          },
          "toughness": {
            "label": "CHARACTERISTIC.TOUGHNESS",
            "short": "T",
            "base": 0,
            "advance": 0,
            "unnatural": 0,
            "cost": 0
          },
          "agility": {
            "label": "CHARACTERISTIC.AGILITY",
            "short": "Ag",
            "base": 0,
            "advance": 0,
            "unnatural": 0,
            "cost": 0
          },
          "intelligence": {
            "label": "CHARACTERISTIC.INTELLIGENCE",
            "short": "Int",
            "base": 0,
            "advance": 0,
            "unnatural": 0,
            "cost": 0
          },
          "perception": {
            "label": "CHARACTERISTIC.PERCEPTION",
            "short": "Per",
            "base": 0,
            "advance": 0,
            "unnatural": 0,
            "cost": 0
          },
          "willpower": {
            "label": "CHARACTERISTIC.WILLPOWER",
            "short": "WP",
            "base": 0,
            "advance": 0,
            "unnatural": 0,
            "cost": 0
          },
          "fellowship": {
            "label": "CHARACTERISTIC.FELLOWSHIP",
            "short": "Fel",
            "base": 0,
            "advance": 0,
            "unnatural": 0,
            "cost": 0
          }
        }
      },
      "skills": {
        "skills": {
          "awareness": {
            "label": "SKILL.AWARENESS",
            "characteristics": [
              "Ag"
            ],
            "advance": -20,
            "isSpecialist": false,
            "specialities": {},
            "cost": 0
          },
          "barter": {
            "label": "SKILL.BARTER",
            "characteristics": [
              "Fel"
            ],
            "advance": -20,
            "isSpecialist": false,
            "specialities": {},
            "cost": 0
          },
          "carouse": {
            "label": "SKILL.CAROUSE",
            "characteristics": [
              "Fel"
            ],
            "advance": -20,
            "isSpecialist": false,
            "specialities": {},
            "cost": 0
          },
          "charm": {
            "label": "SKILL.CHARM",
            "characteristics": [
              "Fel"
            ],
            "advance": -20,
            "isSpecialist": false,
            "specialities": {},
            "cost": 0
          },
		  "climb": {
            "label": "SKILL.CLIMB",
            "characteristics": [
              "S"
            ],
            "advance": -20,
            "isSpecialist": false,
            "specialities": {},
            "cost": 0
          },
          "command": {
            "label": "SKILL.COMMAND",
            "characteristics": [
              "Fel"
            ],
            "advance": -20,
            "isSpecialist": false,
            "specialities": {},
            "cost": 0
          },
          "concealment": {
            "label": "SKILL.CONCEALMENT",
            "characteristics": [
              "Ag"
            ],
            "advance": -20,
            "isSpecialist": false,
            "specialities": {},
            "cost": 0
          },
          "contortionist": {
            "label": "SKILL.CONTORTIONIST",
            "characteristics": [
              "Ag"
            ],
            "advance": -20,
            "isSpecialist": false,
            "specialities": {},
            "cost": 0
          },
          "deceive": {
            "label": "SKILL.DECEIVE",
            "characteristics": [
              "Fel"
            ],
            "advance": -20,
            "isSpecialist": false,
            "specialities": {},
            "cost": 0
          },
          "disguise": {
            "label": "SKILL.DISGUISE",
            "characteristics": [
              "Fel"
            ],
            "advance": -20,
            "isSpecialist": false,
            "specialities": {},
            "cost": 0
          },
          "dodge": {
            "label": "SKILL.DODGE",
            "characteristics": [
              "Ag"
            ],
            "advance": -20,
            "isSpecialist": false,
            "specialities": {},
            "cost": 0
          },
          "evaluate": {
            "label": "SKILL.EVALUATE",
            "characteristics": [
              "Int"
            ],
            "advance": -20,
            "isSpecialist": false,
            "specialities": {},
            "cost": 0
          },
          "gamble": {
            "label": "SKILL.GAMBLE",
            "characteristics": [
              "Int"
            ],
            "advance": -20,
            "isSpecialist": false,
            "specialities": {},
            "cost": 0
          },
          "inquiry": {
            "label": "SKILL.INQUIRY",
            "characteristics": [
              "Fel"
            ],
            "advance": -20,
            "isSpecialist": false,
            "specialities": {},
            "cost": 0
          },
          "Intimidate": {
            "label": "SKILL.INTIMIDATE",
            "characteristics": [
              "S"
            ],
            "advance": -20,
            "isSpecialist": false,
            "specialities": {},
            "cost": 0
          },
          "logic": {
            "label": "SKILL.LOGIC",
            "characteristics": [
              "Int"
            ],
            "advance": -20,
            "isSpecialist": false,
            "specialities": {},
            "cost": 0
          },
          "scrutiny": {
            "label": "SKILL.SCRUTINY",
            "characteristics": [
              "Per"
            ],
            "advance": -20,
            "isSpecialist": false,
            "specialities": {},
            "cost": 0
          },
          "search": {
            "label": "SKILL.SEARCH",
            "characteristics": [
              "Per"
            ],
            "advance": -20,
            "isSpecialist": false,
            "specialities": {},
            "cost": 0
          },
          "silentmove": {
            "label": "SKILL.SILENTMOVE",
            "characteristics": [
              "Ag"
            ],
            "advance": -20,
            "isSpecialist": false,
            "specialities": {},
            "cost": 0
          },
          "swim": {
            "label": "SKILL.SWIM",
            "characteristics": [
              "S"
            ],
            "advance": -20,
            "isSpecialist": false,
            "specialities": {},
            "cost": 0
          },
		  "advancedag": {
            "label": "SKILL.ADVANCEDAG",
            "characteristics": [
              "Ag"
            ],
            "advance": -20,
            "isSpecialist": true,
            "specialities": {
              "acrobatics": {
                "label": "Acrobatics",
                "advance": -20,
                "cost": 0
              },
			  "drivegroundvehicle": {
                "label": "Drive (Ground Vehicle)",
                "advance": -20,
                "cost": 0
              },
			  "driveskimmerhover": {
                "label": "Drive (Skimmer/Hover)",
                "advance": -20,
                "cost": 0
              },
			  "drivewalker": {
                "label": "Drive (Walker)",
                "advance": -20,
                "cost": 0
              },
			  "pilotpersonal": {
                "label": "Pilot (Personal)",
                "advance": -20,
                "cost": 0
              },
			  "pilotflyers": {
                "label": "Pilot (Flyers)",
                "advance": -20,
                "cost": 0
              },
			  "pilotspacecraft": {
                "label": "Pilot (Space Craft)",
                "advance": -20,
                "cost": 0
              },
			  "Security": {
                "label": "Security",
                "advance": -20,
                "cost": 0
              },
			  "shadowing": {
                "label": "Shadowing",
                "advance": -20,
                "cost": 0
              },
			  "sleightofhand": {
                "label": "Sleight of Hand",
                "advance": -20,
                "cost": 0
              },
			  "tradearmourer": {
                "label": "Trade (Armourer)",
                "advance": -20,
                "cost": 0
              },
			  "tradeastrographer": {
                "label": "Trade (Astrographer)",
                "advance": -20,
                "cost": 0
              },
			  "traderemembrancerag": {
                "label": "Trade (Remembrancer(Ag))",
                "advance": -20,
                "cost": 0
              },
			  "tradevoidfarer": {
                "label": "Trade (Voidfarer)",
                "advance": -20,
                "cost": 0
              }
			}
          },
		  "advancedfel": {
            "label": "SKILL.ADVANCEDFEL",
            "characteristics": [
              "Fel"
            ],
            "advance": -20,
            "isSpecialist": true,
            "specialities": {
              "blather": {
                "label": "Blather",
                "advance": -20,
                "cost": 0
              },
			  "commerce": {
                "label": "Commerce",
                "advance": -20,
                "cost": 0
              },
			  "performerdancer": {
                "label": "Performer (Dancer)",
                "advance": -20,
                "cost": 0
              },
			  "performermusician": {
                "label": "Performer (Musician)",
                "advance": -20,
                "cost": 0
              },
			  "performerpreacher": {
                "label": "Performer (Preacher)",
                "advance": -20,
                "cost": 0
              },
			  "performersinger": {
                "label": "Performer (Singer)",
                "advance": -20,
                "cost": 0
              },
			  "performerstoryteller": {
                "label": "Performer (Storyteller)",
                "advance": -20,
                "cost": 0
              },
			  "tradesoothsayer": {
                "label": "Trade (Soothsayer)",
                "advance": -20,
                "cost": 0
              },
			  "tradetrader": {
                "label": "Trade (Trader)",
                "advance": -20,
                "cost": 0
              }
			}
		  },
		  "advancedint": {
            "label": "SKILL.ADVANCEDINT",
            "characteristics": [
              "Int"
            ],
            "advance": -20,
            "isSpecialist": true,
            "specialities": {
              "chemuse": {
                "label": "Chem-Use",
                "advance": -20,
                "cost": 0
              },
			  "ciphersroguetrader": {
                "label": "Ciphers (Rogue Trader)",
                "advance": -20,
                "cost": 0
              },
			  "ciphersmercenarycant": {
                "label": "Ciphers (Mercenary Cant)",
                "advance": -20,
                "cost": 0
              },
			  "ciphersnobiliteencoding": {
                "label": "Ciphers (Nobilite Encoding)",
                "advance": -20,
                "cost": 0
              },
			  "ciphersnobilitefamily": {
                "label": "Ciphers (Nobilite Family)",
                "advance": -20,
                "cost": 0
              },
			  "ciphersastropathsign": {
                "label": "Ciphers (Astropath Sign)",
                "advance": -20,
                "cost": 0
              },
			  "ciphersunderworld": {
                "label": "Ciphers (Underworld)",
                "advance": -20,
                "cost": 0
              },
			  "commonloreadeptusarbites": {
                "label": "Common Lore (Adeptus Arbites)",
                "advance": -20,
                "cost": 0
              },
			  "commonloreadeptusastratelepathica": {
                "label": "Common Lore (Adeptus Astra Telepathica)",
                "advance": -20,
                "cost": 0
              },
			  "commonloreadeptusmechanicus": {
                "label": "Common Lore (Adeptus Mechanicus)",
                "advance": -20,
                "cost": 0
              },
			  "commonloreadministratum": {
                "label": "Common Lore (Administratum)",
                "advance": -20,
                "cost": 0
              },
			  "commonloredarkeldar": {
                "label": "Common Lore (Dark Eldar)",
                "advance": -20,
                "cost": 0
              },
			  "commonloreecchlesiarchy": {
                "label": "Common Lore (Ecchlesiarchy)",
                "advance": -20,
                "cost": 0
              },
			  "commonloreimperialcreed": {
                "label": "Common Lore (Imperial Creed)",
                "advance": -20,
                "cost": 0
              },
			  "commonloreimperialguard": {
                "label": "Common Lore (Imperial Guard)",
                "advance": -20,
                "cost": 0
              },
			  "commonloreimperialnavy": {
                "label": "Common Lore (Imperial Navy)",
                "advance": -20,
                "cost": 0
              },
			  "commonloreimperium": {
                "label": "Common Lore (Imperium)",
                "advance": -20,
                "cost": 0
              },
			  "commonlorekoronusexpanse": {
                "label": "Common Lore (Koronus Expanse)",
                "advance": -20,
                "cost": 0
              },
			  "commonlorenavisnobilite": {
                "label": "Common Lore (Navis Nobilite)",
                "advance": -20,
                "cost": 0
              },
			  "commonloreork": {
                "label": "Common Lore (Ork)",
                "advance": -20,
                "cost": 0
              },
			  "commonloreroguetraders": {
                "label": "Common Lore (Rogue Traders)",
                "advance": -20,
                "cost": 0
              },
			  "commonloretauempire": {
                "label": "Common Lore (Tau Empire)",
                "advance": -20,
                "cost": 0
              },
			  "commonloretech": {
                "label": "Common Lore (Tech)",
                "advance": -20,
                "cost": 0
              },
			  "commonlorewar": {
                "label": "Common Lore (War)",
                "advance": -20,
                "cost": 0
              },
			  "demolition": {
                "label": "Demolition",
                "advance": -20,
                "cost": 0
              },
			  "forbiddenloreadeptusmechanicus": {
                "label": "Forbidden Lore (Adeptus Mechanicus)",
                "advance": -20,
                "cost": 0
              },
			  "forbiddenlorearcheotech": {
                "label": "Forbidden Lore (Archeotech)",
                "advance": -20,
                "cost": 0
              },
			  "forbiddenloredaemonology": {
                "label": "Forbidden Lore (Daemonology)",
                "advance": -20,
                "cost": 0
              },
			  "forbiddenlorewebway": {
                "label": "Forbidden Lore (Webway)",
                "advance": -20,
                "cost": 0
              },
			  "forbiddenloreheresy": {
                "label": "Forbidden Lore (Heresy)",
                "advance": -20,
                "cost": 0
              },
			  "forbiddenloretheinquisition": {
                "label": "Forbidden Lore (The Inquisition)",
                "advance": -20,
                "cost": 0
              },
			  "forbiddenloremutants": {
                "label": "Forbidden Lore (Mutants)",
                "advance": -20,
                "cost": 0
              },
			  "forbiddenlorenavigators": {
                "label": "Forbidden Lore (Navigators)",
                "advance": -20,
                "cost": 0
              },
			  "forbiddenlorepirates": {
                "label": "Forbidden Lore (Pirates)",
                "advance": -20,
                "cost": 0
              },
			  "forbiddenlorepsykers": {
                "label": "Forbidden Lore (Psykers)",
                "advance": -20,
                "cost": 0
              },
			  "forbiddenlorethewarp": {
                "label": "Forbidden Lore (The Warp)",
                "advance": -20,
                "cost": 0
              },
			  "forbiddenlorexenos": {
                "label": "Forbidden Lore (Xenos)",
                "advance": -20,
                "cost": 0
              },
			  "literacy": {
                "label": "Literacy",
                "advance": -20,
                "cost": 0
              },
			  "medicae": {
                "label": "Medicae",
                "advance": -20,
                "cost": 0
              },
			  "navigationsurface": {
                "label": "Navigation (Surface)",
                "advance": -20,
                "cost": 0
              },
			  "navigationstellar": {
                "label": "Navigation (Stellar)",
                "advance": -20,
                "cost": 0
              },
			  "navigationwarp": {
                "label": "Navigation (Warp)",
                "advance": -20,
                "cost": 0
              },
			  "navigationwebway": {
                "label": "Navigation (Webway)",
                "advance": -20,
                "cost": 0
              },
			  "scholasticlorearchaic": {
                "label": "Scholastic Lore (Archaic)",
                "advance": -20,
                "cost": 0
              },
			  "scholasticloreastromancy": {
                "label": "Scholastic Lore (Astromancy)",
                "advance": -20,
                "cost": 0
              },
			  "scholasticlorebeasts": {
                "label": "Scholastic Lore (Beasts)",
                "advance": -20,
                "cost": 0
              },
			  "scholasticlorebureaucracy": {
                "label": "Scholastic Lore (Bureaucracy)",
                "advance": -20,
                "cost": 0
              },
			  "scholasticlorechymistry": {
                "label": "Scholastic Lore (Chymistry)",
                "advance": -20,
                "cost": 0
              },
			  "scholasticlorecryptology": {
                "label": "Scholastic Lore (Cryptology)",
                "advance": -20,
                "cost": 0
              },
			  "scholasticloredrusianchronicles": {
                "label": "Scholastic Lore (Drusian Chronicles)",
                "advance": -20,
                "cost": 0
              },
			  "scholasticloreheraldry": {
                "label": "Scholastic Lore (Heraldry)",
                "advance": -20,
                "cost": 0
              },
			  "scholasticloreheraldry": {
                "label": "Scholastic Lore (Heraldry)",
                "advance": -20,
                "cost": 0
              },
			  "scholasticloreimperialwarrants": {
                "label": "Scholastic Lore (Imperial Warrants)",
                "advance": -20,
                "cost": 0
              },
			  "scholasticloreimperialcreed": {
                "label": "Scholastic Lore (Imperial Creed)",
                "advance": -20,
                "cost": 0
              },
			  "scholasticlorejudgement": {
                "label": "Scholastic Lore (Judgement)",
                "advance": -20,
                "cost": 0
              },
			  "scholasticlorelegend": {
                "label": "Scholastic Lore (Legend)",
                "advance": -20,
                "cost": 0
              },
			  "scholasticlorenavisnobilite": {
                "label": "Scholastic Lore (Navis Nobilite)",
                "advance": -20,
                "cost": 0
              },
			  "scholasticlorenumerology": {
                "label": "Scholastic Lore (Numerology)",
                "advance": -20,
                "cost": 0
              },
			  "scholasticloreoccult": {
                "label": "Scholastic Lore (Occult)",
                "advance": -20,
                "cost": 0
              },
			  "scholasticlorephilosophy": {
                "label": "Scholastic Lore (Philosophy)",
                "advance": -20,
                "cost": 0
              },
			  "scholasticloretacticaimperialis": {
                "label": "Scholastic Lore (Tactica Imperialis)",
                "advance": -20,
                "cost": 0
              },
			  "scholasticloretauempire": {
                "label": "Scholastic Lore (Tau Empire)",
                "advance": -20,
                "cost": 0
              },
			  "secrettongueadministratum": {
                "label": "Secret Tongue (Administratum)",
                "advance": -20,
                "cost": 0
              },
			  "secrettongueecchlesiarchy": {
                "label": "Secret Tongue (Ecchlesiarchy)",
                "advance": -20,
                "cost": 0
              },
			  "secrettonguemilitary": {
                "label": "Secret Tongue (Military)",
                "advance": -20,
                "cost": 0
              },
			  "secrettonguenavigator": {
                "label": "Secret Tongue (Navigator)",
                "advance": -20,
                "cost": 0
              },
			  "secrettonguepirates": {
                "label": "Secret Tongue (Pirates)",
                "advance": -20,
                "cost": 0
              },
			  "secrettongueroguetrader": {
                "label": "Secret Tongue (Rogue Trader)",
                "advance": -20,
                "cost": 0
              },
			  "secrettonguetech": {
                "label": "Secret Tongue (Tech)",
                "advance": -20,
                "cost": 0
              },
			  "secrettongueunderdeck": {
                "label": "Secret Tongue (Underdeck)",
                "advance": -20,
                "cost": 0
              },
			  "speaklanguagedarkeldar": {
                "label": "Speak Language (Dark Eldar)",
                "advance": -20,
                "cost": 0
              },
			  "speaklanguageeldar": {
                "label": "Speak Language (Eldar)",
                "advance": -20,
                "cost": 0
              },
			  "speaklanguageexploratorbinary": {
                "label": "Speak Language (Explorator Binary)",
                "advance": -20,
                "cost": 0
              },
			  "speaklanguagehighgothic": {
                "label": "Speak Language (High Gothic)",
                "advance": -20,
                "cost": 0
              },
			  "speaklanguagelowgothic": {
                "label": "Speak Language (Low Gothic)",
                "advance": -20,
                "cost": 0
              },
			  "speaklanguagekroot": {
                "label": "Speak Language (Kroot)",
                "advance": -20,
                "cost": 0
              },
			  "speaklanguageork": {
                "label": "Speak Language (Ork)",
                "advance": -20,
                "cost": 0
              },
			  "speaklanguagetau": {
                "label": "Speak Language (Tau)",
                "advance": -20,
                "cost": 0
              },
			  "speaklanguagetechnalingua": {
                "label": "Speak Language (Techna-Lingua)",
                "advance": -20,
                "cost": 0
              },
			  "speaklanguagetraderscant": {
                "label": "Speak Language (Trader's Cant)",
                "advance": -20,
                "cost": 0
              },
			  "survival": {
                "label": "Survival",
                "advance": -20,
                "cost": 0
              },
			  "techuse": {
                "label": "Tech-Use",
                "advance": -20,
                "cost": 0
              },
			  "tracking": {
                "label": "Tracking",
                "advance": -20,
                "cost": 0
              },
			  "tradearchaeologist": {
                "label": "Trade (Archaeologist)",
                "advance": -20,
                "cost": 0
              },
			  "tradechymist": {
                "label": "Trade (Chymist)",
                "advance": -20,
                "cost": 0
              },
			  "tradecryptographer": {
                "label": "Trade (Cryptographer)",
                "advance": -20,
                "cost": 0
              },
			  "tradeexplorator": {
                "label": "Trade (Explorator)",
                "advance": -20,
                "cost": 0
              },
			  "tradelinguist": {
                "label": "Trade (Linguist)",
                "advance": -20,
                "cost": 0
              },
			  "traderemembrancerint": {
                "label": "Trade (Remembrancer (Int))",
                "advance": -20,
                "cost": 0
              },
			  "tradeshipwright": {
                "label": "Trade (Shipwright)",
                "advance": -20,
                "cost": 0
              },
			  "tradetechnomat": {
                "label": "Trade (Technomat)",
                "advance": -20,
                "cost": 0
              },
			  "wrangling": {
                "label": "Wrangling",
                "advance": -20,
                "cost": 0
              }
			}
		  },
		  "advancedper": {
            "label": "SKILL.ADVANCEDPER",
            "characteristics": [
              "Per"
            ],
            "advance": -20,
            "isSpecialist": true,
            "specialities": {
              "psyniscience": {
                "label": "Psyniscience",
                "advance": -20,
                "cost": 0
              }
			}
		  },
		  "advancedwp": {
            "label": "SKILL.ADVANCEDWP",
            "characteristics": [
              "WP"
            ],
            "advance": -20,
            "isSpecialist": true,
            "specialities": {
              "interrogation": {
                "label": "Interrogation",
                "advance": -20,
                "cost": 0
              },
			  "invocation": {
                "label": "Invocation",
                "advance": -20,
                "cost": 0
              }
			}
		  }
        }
      },
      "initiative": {
        "initiative": {
          "characteristic": "agility",
          "base": "1d10"
        }
      },
      "wounds": {
        "wounds": {
          "max": 0,
          "value": 0,
          "critical": 0
        }
      },
      "fatigue": {
        "fatigue": {
          "max": 0,
          "value": 0
        }
      },
      "fate": {
        "fate": {
          "max": 0,
          "value": 0
        }
      },
      "psy": {
        "psy": {
          "rating": 0,
          "sustained": 0,
          "class": "bound",
          "cost": 0
        }
      }
    },
    "acolyte": {
      "templates": [
        "characteristics",
        "skills",
        "initiative",
        "wounds",
        "fatigue",
        "fate",
        "psy"
      ],
      "bio": {
        "homeWorld": "",
        "background": "",
        "role": "",
        "elite": "",
        "divination": "",
        "gender": "",
        "age": "",
        "build": "",
        "complexion": "",
        "hair": "",
        "quirks": "",
        "superstition": "",
        "momentos": "",
		"height": "",
		"weight": "",
		"eyes": "",
		"lureOfTheVoid": "",
		"trialsAndTravails": "",
        "notes": ""
      },
      "experience": {
        "value": 0
      },
      "insanity": 0,
      "corruption": 0,
      "aptitudes": {},
      "size": 4
    },
    "npc": {
      "templates": [
        "characteristics",
        "skills",
        "initiative",
        "wounds",
        "fatigue",
        "fate",
        "psy"
      ],
      "experience": {
        "value": 0
      },
      "faction": "",
      "subfaction": "",
      "type": "troop",
      "threatLevel": 0,
      "size": 4
    }
  },
  "Item": {
    "types": [
      "ammunition",
      "aptitude",
      "armour",
      "criticalInjury",
      "cybernetic",
      "drug",
      "forceField",
      "gear",
      "malignancy",
      "mentalDisorder",
      "mutation",
      "psychicPower",
      "specialAbility",
      "talent",
      "tool",
      "trait",
      "weapon",
      "weaponModification"
    ],
    "templates": {
      "equipment": {
        "craftsmanship": "common",
        "description": "",
        "availability": "common",
        "weight": 0
      },
      "itemDescription": {
        "description": "",
        "source": ""
      }
    },
    "ammunition": {
      "templates": [ "equipment" ],
      "quantity": 0,
      "effect": {
        "damage": {
          "modifier": 0,
          "type": "impact"
        },
        "special": "",
        "penetration": "",
        "attack": {
          "modifier": 0
        }
      },
      "weapon": ""
    },
    "armour": {
      "templates": [ "equipment" ],
      "type": "basic",
      "part": {
        "head": 0,
        "leftArm": 0,
        "rightArm": 0,
        "body": 0,
        "leftLeg": 0,
        "rightLeg": 0
      },
      "maxAgility": 0
    },
    "criticalInjury": {
      "templates": ["itemDescription"],
      "type": "impact",
      "part": "body"
    },
    "cybernetic": {
      "templates": [ "equipment" ],
      "installed": false
    },
    "drug": {
      "templates": [ "equipment" ],
      "shortDescription": ""
    },
    "forceField": {
      "templates": [ "equipment" ],
      "protectionRating": 0,
      "overloadChance": 0
    },
    "gear": {
      "templates": [ "equipment" ],
      "shortDescription": ""
    },
    "malignancy": {
      "templates": ["itemDescription"]
    },
    "mentalDisorder": {
      "templates": ["itemDescription"]
    },
    "mutation": {
      "templates": ["itemDescription"]
    },
    "psychicPower": {
      "templates": ["itemDescription"],
      "shortDescription": "",
      "cost": 0,
      "prerequisite": "",
      "action": "",
      "focusPower": {
        "difficulty": 0,
        "test": ""
      },
      "range": "",
      "sustained": "",
      "subtype": "",
      "effect": "",
      "damage": {
        "zone": "bolt",
        "type": "energy",
        "formula": "",
        "penetration": "",
        "special": ""
      }
    },
    "specialAbility": {
      "templates": ["itemDescription"],
      "benefit": ""
    },
    "talent": {
      "templates": ["itemDescription"],
      "prerequisites": "",
      "aptitudes": "",
      "benefit": "",
      "tier": 0,
      "cost": 0
    },
    "tool": {
      "templates": [ "equipment" ],
      "shortDescription": ""
    },
    "trait": {
      "templates": ["itemDescription"],
      "benefit": ""
    },
    "weapon": {
      "templates": [ "equipment" ],
      "class": "",
      "type": "",
      "range": 0,
      "rateOfFire": {
        "single": 0,
        "burst": 0,
        "full": 0
      },
      "damage": "",
      "damageType": "impact",
      "penetration": "",
      "clip": {
        "max": 0,
        "value": 0
      },
      "reload": "",
      "special": "",
      "attack": 0
    },
    "weaponModification": {
      "templates": [ "equipment" ],
      "upgrades": "",
      "installed": false
    },
    "aptitude" : {
      "templates": ["itemDescription"]
    }
  }
}
